langchain_agentbay_integration/.DS_Store
langchain_agentbay_integration/__init__.py
langchain_agentbay_integration/py.typed
langchain_agentbay_integration/self_evolving/mobile_tools_documentation.md
langchain_agentbay_integration/self_evolving/self_evolving_agent.py
langchain_agentbay_integration/self_evolving/self_evolving_web_visualizer.py
langchain_agentbay_integration/toolkits.py
langchain_agentbay_integration/tools.py
langchain_agentbay_integration-0.2.0.dist-info/METADATA
langchain_agentbay_integration-0.2.0.dist-info/WHEEL
langchain_agentbay_integration-0.2.0.dist-info/licenses/LICENSE
langchain_agentbay_integration-0.2.0.dist-info/RECORD
