Metadata-Version: 2.4
Name: langchain-agentbay-integration
Version: 0.2.0
Summary: Integration package for AgentBay with LangChain
License: MIT
License-File: LICENSE
Requires-Python: >=3.10,<4.0
Classifier: License :: OSI Approved :: MIT License
Classifier: Programming Language :: Python :: 3
Classifier: Programming Language :: Python :: 3.10
Classifier: Programming Language :: Python :: 3.11
Classifier: Programming Language :: Python :: 3.12
Classifier: Programming Language :: Python :: 3.13
Classifier: Programming Language :: Python :: 3.14
Requires-Dist: dashscope (>=1.24.8,<2.0.0)
Requires-Dist: langchain (>=1.0.3,<2.0.0)
Requires-Dist: nest-asyncio (>=1.6.0,<2.0.0)
Requires-Dist: playwright (>=1.55.0,<2.0.0)
Requires-Dist: pydantic (>=2.0.0,<3.0.0)
Requires-Dist: wuying-agentbay-sdk (>=0.9.0,<0.10.0)
Project-URL: Repository, https://github.com/langchain-ai/langchain
Project-URL: Release Notes, https://github.com/langchain-ai/langchain/releases?q=tag%3A%22agentbay-integration%3D%3D0%22&expanded=true
Project-URL: Source Code, https://github.com/langchain-ai/langchain/tree/master/libs/partners/agentbay-integration
